{
  "type": "minecraft:range_choice",
  "input": {
    "type": "minecraft:add",
    "argument1": 0.02,
    "argument2": {
      "type": "minecraft:mul",
      "argument1": 1.2,
      "argument2": {
        "type": "minecraft:flat_cache",
        "argument": {
          "type": "minecraft:noise",
          "noise": "ascension:ascension_continents_noise",
          "xz_scale": 0.08,
          "y_scale": 0.0
        }
      }
    }
  },
  "max_exclusive": -0.35,
  "min_inclusive": -10.0,
  "when_in_range": -1.2,
  "when_out_of_range": {
    "type": "minecraft:range_choice",
    "input": {
      "type": "minecraft:add",
      "argument1": 0.02,
      "argument2": {
        "type": "minecraft:mul",
        "argument1": 1.2,
        "argument2": {
          "type": "minecraft:flat_cache",
          "argument": {
            "type": "minecraft:noise",
            "noise": "ascension:ascension_continents_noise",
            "xz_scale": 0.08,
            "y_scale": 0.0
          }
        }
      }
    },
    "max_exclusive": -0.12,
    "min_inclusive": -0.35,
    "when_in_range": -0.4,
    "when_out_of_range": {
      "type": "minecraft:range_choice",
      "input": {
        "type": "minecraft:add",
        "argument1": 0.02,
        "argument2": {
          "type": "minecraft:mul",
          "argument1": 1.2,
          "argument2": {
            "type": "minecraft:flat_cache",
            "argument": {
              "type": "minecraft:noise",
              "noise": "ascension:ascension_continents_noise",
              "xz_scale": 0.08,
              "y_scale": 0.0
            }
          }
        }
      },
      "max_exclusive": 0.2,
      "min_inclusive": -0.12,
      "when_in_range": 0.25,
      "when_out_of_range": 0.9
    }
  }
}